{"Users":[{"Id":1,"UserName":"Bob","Todos":null},{"Id":2,"UserName":"John","Todos":null},{"Id":3,"UserName":"Peter","Todos":null},{"Id":4,"UserName":"Lars","Todos":null},{"Id":5,"UserName":"Troels","Todos":null},{"Id":6,"UserName":"Test1234","Todos":null}],"Todos":[{"Id":1,"Owner":{"Id":1,"UserName":"Bob","Todos":null},"Title":"string","IsCompleted":false},{"Id":2,"Owner":{"Id":2,"UserName":"John","Todos":null},"Title":"Test 1","IsCompleted":false},{"Id":3,"Owner":{"Id":1,"UserName":"Bob","Todos":null},"Title":"Hello there?","IsCompleted":false},{"Id":4,"Owner":{"Id":3,"UserName":"Peter","Todos":null},"Title":"Hej med dig!","IsCompleted":false},{"Id":5,"Owner":{"Id":6,"UserName":"Test1234","Todos":null},"Title":"123","IsCompleted":false},{"Id":6,"Owner":{"Id":1,"UserName":"Bob","Todos":null},"Title":"123","IsCompleted":false},{"Id":7,"Owner":{"Id":1,"UserName":"Bob","Todos":null},"Title":"123","IsCompleted":false},{"Id":8,"Owner":{"Id":2,"UserName":"John","Todos":null},"Title":"123","IsCompleted":false},{"Id":9,"Owner":{"Id":2,"UserName":"John","Todos":null},"Title":"123","IsCompleted":false},{"Id":10,"Owner":{"Id":2,"UserName":"John","Todos":null},"Title":"123","IsCompleted":false},{"Id":11,"Owner":{"Id":2,"UserName":"John","Todos":null},"Title":"123","IsCompleted":false},{"Id":12,"Owner":{"Id":2,"UserName":"John","Todos":null},"Title":"123","IsCompleted":false}]}